setup.py
budoc/__init__.py
budoc/budoc.py
budoc/cmd.py
budoc/config.py
budoc/pydoc.py
budoc.egg-info/PKG-INFO
budoc.egg-info/SOURCES.txt
budoc.egg-info/dependency_links.txt
budoc.egg-info/entry_points.txt
budoc.egg-info/not-zip-safe
budoc.egg-info/requires.txt
budoc.egg-info/top_level.txt