Metadata-Version: 1.1
Name: budoc
Version: 0.2
Summary: A command line tool and library to auto generate API documentation to Markdown file for Python libraries.
Home-page: http://github.com/zeaphoo/budoc/
Author: zeaphoo
Author-email: zeaphoo@gmail.com
License: BSD
Download-URL: http://github.com/zeaphoo/budoc/tarball/0.1
Platform: any
Classifier: Development Status :: 4 - Beta
Classifier: Environment :: Web Environment
Classifier: Intended Audience :: Developers
Classifier: License :: OSI Approved :: MIT License
Classifier: Operating System :: OS Independent
Classifier: Programming Language :: Python
Classifier: Programming Language :: Python :: 3
Classifier: Topic :: Internet :: WWW/HTTP :: Dynamic Content
Classifier: Topic :: Software Development :: Libraries :: Python Modules
